{
  "kind": "collectionType",
  "collectionName": "majors",
  "info": {
    "name": "Major"
  },
  "options": {
    "increments": true,
    "timestamps": true,
    "draftAndPublish": true
  },
  "pluginOptions": {},
  "attributes": {
    "Image": {
      "model": "file",
      "via": "related",
      "allowedTypes": [
        "images",
        "files",
        "videos"
      ],
      "plugin": "upload",
      "required": false,
      "pluginOptions": {}
    },
    "title_major": {
      "type": "string"
    },
    "link": {
      "type": "string"
    },
    "decs": {
      "type": "text"
    }
  }
}
